{
  "Name": "azure-mgmt-storagecache",
  "Version": "0.5.0",
  "sdkCSV": {
    "DisplayName": "Resource Management - Storage Cache",
    "ServiceName": "Storage Cache",
    "Type": "mgmt",
    "New": "False",
    "RepoPath": "storage",
    "Support": "deprecated",
    "EOLDate": "3/31/2023",
    "Hide": "true",
    "MSDocService": ""
  },
  "DocsConfig": {
    "package_info": {
      "url": "https://github.com/Azure/azure-sdk-for-python.git",
      "branch": "master",
      "folder": "azure-mgmt-storagecache",
      "install_type": "pypi",
      "name": "azure-mgmt-storagecache",
      "version": "==0.5.0"
    }
  }
}
