{
  "Name": "azure-mgmt-dnsresolver",
  "Version": "1.1.0",
  "DevVersion": null,
  "DirectoryPath": "sdk/dnsresolver/azure-mgmt-dnsresolver",
  "ServiceDirectory": "dnsresolver",
  "ReadMePath": "sdk/dnsresolver/azure-mgmt-dnsresolver/README.md",
  "ChangeLogPath": "sdk/dnsresolver/azure-mgmt-dnsresolver/CHANGELOG.md",
  "Group": null,
  "SdkType": "mgmt",
  "IsNewSdk": true,
  "ArtifactName": "azure-mgmt-dnsresolver",
  "ReleaseStatus": "2025-06-16",
  "IncludedForValidation": false,
  "AdditionalValidationPackages": [
    ""
  ],
  "ArtifactDetails": {
    "triggeringPaths": [
      "/sdk/dnsresolver/ci.yml"
    ],
    "safeName": "azuremgmtdnsresolver",
    "name": "azure-mgmt-dnsresolver"
  },
  "CIParameters": {
    "CIMatrixConfigs": []
  },
  "Namespaces": [
    "azure.mgmt.dnsresolver"
  ]
}
