{
  "Name": "azure-ai-vision-imageanalysis",
  "Version": "1.0.0",
  "DevVersion": null,
  "DirectoryPath": "sdk/vision/azure-ai-vision-imageanalysis",
  "ServiceDirectory": "vision",
  "ReadMePath": "sdk/vision/azure-ai-vision-imageanalysis/README.md",
  "ChangeLogPath": "sdk/vision/azure-ai-vision-imageanalysis/CHANGELOG.md",
  "Group": null,
  "SdkType": "client",
  "IsNewSdk": true,
  "ArtifactName": "azure-ai-vision-imageanalysis",
  "ReleaseStatus": "2024-10-18",
  "IncludedForValidation": false,
  "AdditionalValidationPackages": [
    ""
  ],
  "ArtifactDetails": {
    "name": "azure-ai-vision-imageanalysis",
    "safeName": "azureaivisionimageanalysis"
  },
  "Namespaces": [
    "azure.ai.vision.imageanalysis"
  ]
}
