{
  "Name": "azure-mgmt-containerservice",
  "Version": "35.0.0",
  "DevVersion": null,
  "DirectoryPath": "sdk/containerservice/azure-mgmt-containerservice",
  "ServiceDirectory": "containerservice",
  "ReadMePath": "sdk/containerservice/azure-mgmt-containerservice/README.md",
  "ChangeLogPath": "sdk/containerservice/azure-mgmt-containerservice/CHANGELOG.md",
  "Group": null,
  "SdkType": "mgmt",
  "IsNewSdk": true,
  "ArtifactName": "azure-mgmt-containerservice",
  "ReleaseStatus": "2025-04-14",
  "IncludedForValidation": false,
  "AdditionalValidationPackages": [
    ""
  ],
  "ArtifactDetails": {
    "triggeringPaths": [
      "/sdk/containerservice/ci.yml"
    ],
    "safeName": "azuremgmtcontainerservice",
    "name": "azure-mgmt-containerservice"
  },
  "CIParameters": {
    "CIMatrixConfigs": []
  },
  "Namespaces": [
    "azure.mgmt.containerservice"
  ],
  "CIMatrixConfigs": [],
  "DocsCiConfigProperties": {
    "build_in_subpackage": true,
    "package_info": {
      "prefer_source_distribution": false
    }
  }
}
