{
  "Name": "azure-mgmt-appplatform",
  "Version": "9.0.0",
  "DevVersion": null,
  "DirectoryPath": "sdk/appplatform/azure-mgmt-appplatform",
  "ServiceDirectory": "appplatform",
  "ReadMePath": "sdk/appplatform/azure-mgmt-appplatform/README.md",
  "ChangeLogPath": "sdk/appplatform/azure-mgmt-appplatform/CHANGELOG.md",
  "Group": null,
  "SdkType": "mgmt",
  "IsNewSdk": true,
  "ArtifactName": "azure-mgmt-appplatform",
  "ReleaseStatus": "2024-01-26",
  "DocsCiConfigProperties": {
    "package_info": {
      "prefer_source_distribution": false
    }
  },
  "Namespaces": [
    "azure.mgmt.appplatform"
  ]
}
