{
  "Name": "azure-mgmt-purview",
  "Version": "1.1.0a20260126001",
  "DevVersion": "1.1.0a20260126001",
  "DirectoryPath": "sdk/purview/azure-mgmt-purview",
  "ServiceDirectory": "purview",
  "ReadMePath": "sdk/purview/azure-mgmt-purview/README.md",
  "ChangeLogPath": "sdk/purview/azure-mgmt-purview/CHANGELOG.md",
  "Group": null,
  "SdkType": "mgmt",
  "IsNewSdk": true,
  "ArtifactName": "azure-mgmt-purview",
  "ReleaseStatus": "2022-11-07",
  "IncludedForValidation": false,
  "AdditionalValidationPackages": [
    ""
  ],
  "ArtifactDetails": {
    "triggeringPaths": [
      "/sdk/purview/ci.yml"
    ],
    "name": "azure-mgmt-purview",
    "safeName": "azuremgmtpurview"
  },
  "CIParameters": {
    "CIMatrixConfigs": []
  },
  "SpecProjectPath": null,
  "Namespaces": [
    "azure.mgmt.purview"
  ]
}
