{
  "Name": "azure-communication-jobrouter",
  "Version": "1.0.0a20230803001",
  "DevVersion": "1.0.0a20230803001",
  "DirectoryPath": "sdk/communication/azure-communication-jobrouter",
  "ServiceDirectory": "communication",
  "ReadMePath": "sdk/communication/azure-communication-jobrouter/README.md",
  "ChangeLogPath": "sdk/communication/azure-communication-jobrouter/CHANGELOG.md",
  "Group": null,
  "SdkType": "client",
  "IsNewSdk": true,
  "ArtifactName": "azure-communication-jobrouter",
  "ReleaseStatus": "Unreleased",
  "DocsCiConfigProperties": {
    "extension_config": {
      "autodoc_default_options": {
        "inherited-members": 1
      }
    }
  }
}
