{
  "Name": "azure-ai-vision-imageanalysis",
  "Version": "1.0.0b2",
  "DevVersion": null,
  "DirectoryPath": "sdk/vision/azure-ai-vision-imageanalysis",
  "ServiceDirectory": "vision",
  "ReadMePath": "sdk/vision/azure-ai-vision-imageanalysis/README.md",
  "ChangeLogPath": "sdk/vision/azure-ai-vision-imageanalysis/CHANGELOG.md",
  "Group": null,
  "SdkType": "client",
  "IsNewSdk": true,
  "ArtifactName": "azure-ai-vision-imageanalysis",
  "ReleaseStatus": "2024-02-09",
  "Namespaces": [
    "azure.ai.vision.imageanalysis"
  ]
}
