{
  "Name": "azure-mgmt-mongocluster",
  "Version": "1.0.0a20241209001",
  "DevVersion": null,
  "DirectoryPath": "sdk/mongocluster/azure-mgmt-mongocluster",
  "ServiceDirectory": "mongocluster",
  "ReadMePath": "sdk/mongocluster/azure-mgmt-mongocluster/README.md",
  "ChangeLogPath": "sdk/mongocluster/azure-mgmt-mongocluster/CHANGELOG.md",
  "Group": null,
  "SdkType": "mgmt",
  "IsNewSdk": true,
  "ArtifactName": "azure-mgmt-mongocluster",
  "ReleaseStatus": null,
  "IncludedForValidation": false,
  "AdditionalValidationPackages": [
    ""
  ],
  "ArtifactDetails": {
    "name": "azure-mgmt-mongocluster",
    "safeName": "azuremgmtmongocluster"
  },
  "CIMatrixConfigs": [],
  "Namespaces": [
    "azure.mgmt.mongocluster"
  ]
}
