{
  "Name": "azure-mgmt-web",
  "Version": "7.3.0a20240808001",
  "DevVersion": "7.3.0a20240808001",
  "DirectoryPath": "sdk/appservice/azure-mgmt-web",
  "ServiceDirectory": "appservice",
  "ReadMePath": "sdk/appservice/azure-mgmt-web/README.md",
  "ChangeLogPath": "sdk/appservice/azure-mgmt-web/CHANGELOG.md",
  "Group": null,
  "SdkType": "mgmt",
  "IsNewSdk": true,
  "ArtifactName": "azure-mgmt-web",
  "ReleaseStatus": "2024-06-17",
  "DependentPackages": null,
  "Namespaces": [
    "azure.mgmt.web"
  ]
}
