{
  "Name": "azure-mgmt-powerbiembedded",
  "Version": "3.0.0a20260123001",
  "DevVersion": "3.0.0a20260123001",
  "DirectoryPath": "sdk/powerbiembedded/azure-mgmt-powerbiembedded",
  "ServiceDirectory": "powerbiembedded",
  "ReadMePath": "sdk/powerbiembedded/azure-mgmt-powerbiembedded/README.md",
  "ChangeLogPath": "sdk/powerbiembedded/azure-mgmt-powerbiembedded/CHANGELOG.md",
  "Group": null,
  "SdkType": "mgmt",
  "IsNewSdk": true,
  "ArtifactName": "azure-mgmt-powerbiembedded",
  "ReleaseStatus": "2024-06-24",
  "IncludedForValidation": false,
  "AdditionalValidationPackages": [
    ""
  ],
  "ArtifactDetails": {
    "name": "azure-mgmt-powerbiembedded",
    "safeName": "azuremgmtpowerbiembedded",
    "triggeringPaths": [
      "/sdk/powerbiembedded/ci.yml"
    ]
  },
  "CIParameters": {
    "CIMatrixConfigs": []
  },
  "SpecProjectPath": null,
  "Namespaces": [
    "azure.mgmt.powerbiembedded"
  ]
}
