{
  "Name": "azure-ai-projects",
  "Version": "2.0.0a20260303005",
  "DevVersion": "2.0.0a20260303005",
  "DirectoryPath": "sdk/ai/azure-ai-projects",
  "ServiceDirectory": "ai",
  "ReadMePath": "sdk/ai/azure-ai-projects/README.md",
  "ChangeLogPath": "sdk/ai/azure-ai-projects/CHANGELOG.md",
  "Group": null,
  "SdkType": "client",
  "IsNewSdk": true,
  "ArtifactName": "azure-ai-projects",
  "ReleaseStatus": "2026-03-06",
  "IncludedForValidation": false,
  "AdditionalValidationPackages": [
    ""
  ],
  "ArtifactDetails": {
    "name": "azure-ai-projects",
    "safeName": "azureaiprojects",
    "triggeringPaths": [
      "/sdk/ai/ci.yml"
    ]
  },
  "CIParameters": {
    "CIMatrixConfigs": []
  },
  "SpecProjectPath": "specification/ai-foundry/data-plane/Foundry",
  "Namespaces": [
    "azure.ai.projects"
  ],
  "CIMatrixConfigs": []
}
