{
  "Name": "azure-mgmt-cdn",
  "Version": "13.1.1a20250206001",
  "DevVersion": null,
  "DirectoryPath": "sdk/cdn/azure-mgmt-cdn",
  "ServiceDirectory": "cdn",
  "ReadMePath": "sdk/cdn/azure-mgmt-cdn/README.md",
  "ChangeLogPath": "sdk/cdn/azure-mgmt-cdn/CHANGELOG.md",
  "Group": null,
  "SdkType": "mgmt",
  "IsNewSdk": true,
  "ArtifactName": "azure-mgmt-cdn",
  "ReleaseStatus": null,
  "IncludedForValidation": false,
  "AdditionalValidationPackages": [
    ""
  ],
  "ArtifactDetails": {
    "safeName": "azuremgmtcdn",
    "name": "azure-mgmt-cdn"
  },
  "CIMatrixConfigs": [],
  "Namespaces": [
    "azure.mgmt.cdn"
  ],
  "DocsCiConfigProperties": {
    "package_info": {
      "prefer_source_distribution": false
    }
  }
}
