{
  "Name": "azure-mgmt-peering",
  "Version": "2.0.0b2",
  "DevVersion": null,
  "DirectoryPath": "sdk/peering/azure-mgmt-peering",
  "ServiceDirectory": "peering",
  "ReadMePath": "sdk/peering/azure-mgmt-peering/README.md",
  "ChangeLogPath": "sdk/peering/azure-mgmt-peering/CHANGELOG.md",
  "Group": null,
  "SdkType": "mgmt",
  "IsNewSdk": true,
  "ArtifactName": "azure-mgmt-peering",
  "ReleaseStatus": "2026-03-27",
  "IncludedForValidation": false,
  "AdditionalValidationPackages": [
    ""
  ],
  "ArtifactDetails": {
    "triggeringPaths": [
      "/sdk/peering/ci.yml"
    ],
    "name": "azure-mgmt-peering",
    "safeName": "azuremgmtpeering"
  },
  "CIParameters": {
    "CIMatrixConfigs": []
  },
  "SpecProjectPath": "specification/peering/resource-manager/Microsoft.Peering/Peering",
  "Namespaces": [
    "azure.mgmt.peering"
  ]
}
