{
  "Name": "azure-monitor-opentelemetry-exporter",
  "Version": "1.0.0a20251113001",
  "DevVersion": "1.0.0a20251113001",
  "DirectoryPath": "sdk/monitor/azure-monitor-opentelemetry-exporter",
  "ServiceDirectory": "monitor",
  "ReadMePath": "sdk/monitor/azure-monitor-opentelemetry-exporter/README.md",
  "ChangeLogPath": "sdk/monitor/azure-monitor-opentelemetry-exporter/CHANGELOG.md",
  "Group": null,
  "SdkType": "client",
  "IsNewSdk": true,
  "ArtifactName": "azure-monitor-opentelemetry-exporter",
  "ReleaseStatus": "Unreleased",
  "IncludedForValidation": false,
  "AdditionalValidationPackages": [
    ""
  ],
  "ArtifactDetails": {
    "triggeringPaths": [
      "/sdk/monitor/ci.yml"
    ],
    "name": "azure-monitor-opentelemetry-exporter",
    "safeName": "azuremonitoropentelemetryexporter"
  },
  "CIParameters": {
    "CIMatrixConfigs": []
  },
  "Namespaces": [
    "azure.monitor.opentelemetry.exporter"
  ],
  "CIMatrixConfigs": [],
  "DocsCiConfigProperties": {
    "package_info": {
      "prefer_source_distribution": false
    }
  }
}
