{
  "Name": "azure-developer-devcenter",
  "Version": "1.0.1a20241203001",
  "DevVersion": null,
  "DirectoryPath": "sdk/devcenter/azure-developer-devcenter",
  "ServiceDirectory": "devcenter",
  "ReadMePath": "sdk/devcenter/azure-developer-devcenter/README.md",
  "ChangeLogPath": "sdk/devcenter/azure-developer-devcenter/CHANGELOG.md",
  "Group": null,
  "SdkType": "client",
  "IsNewSdk": true,
  "ArtifactName": "azure-developer-devcenter",
  "ReleaseStatus": null,
  "IncludedForValidation": false,
  "AdditionalValidationPackages": [
    ""
  ],
  "ArtifactDetails": {
    "name": "azure-developer-devcenter",
    "safeName": "azuredeveloperdevcenter"
  },
  "CIMatrixConfigs": [],
  "Namespaces": [
    "azure.developer.devcenter"
  ]
}
