{
  "Name": "azure-eventgrid",
  "Version": "4.22.0a20260123001",
  "DevVersion": "4.22.0a20260123001",
  "DirectoryPath": "sdk/eventgrid/azure-eventgrid",
  "ServiceDirectory": "eventgrid",
  "ReadMePath": "sdk/eventgrid/azure-eventgrid/README.md",
  "ChangeLogPath": "sdk/eventgrid/azure-eventgrid/CHANGELOG.md",
  "Group": null,
  "SdkType": "client",
  "IsNewSdk": true,
  "ArtifactName": "azure-eventgrid",
  "ReleaseStatus": "2025-05-14",
  "IncludedForValidation": false,
  "AdditionalValidationPackages": [
    ""
  ],
  "ArtifactDetails": {
    "name": "azure-eventgrid",
    "triggeringPaths": [
      "/sdk/eventgrid/ci.yml"
    ],
    "safeName": "azureeventgrid"
  },
  "CIParameters": {
    "CIMatrixConfigs": []
  },
  "SpecProjectPath": "specification/eventgrid/Azure.Messaging.EventGrid",
  "Namespaces": [
    "azure.eventgrid"
  ]
}
